{
    "/scripts/blocks.js": "/scripts/blocks.js?id=53d9e75ce0b191a34976",
    "/styles/login.css": "/styles/login.css?id=6ac7c43b8faab8ed5e56",
    "/styles/admin.css": "/styles/admin.css?id=6d44bf7664d20243b1c0",
    "/styles/theme.css": "/styles/theme.css?id=510bceaaa0fcfcc4e1a9",
    "/styles/editor.css": "/styles/editor.css?id=9a06fa6bbe77f3df17fa",
    "/scripts/blocks.js.map": "/scripts/blocks.js.map?id=256df97413e16de5f36c",
    "/styles/login.css.map": "/styles/login.css.map?id=5c1dc0140d879ecf9970",
    "/styles/admin.css.map": "/styles/admin.css.map?id=6ad5447136bd2f984c9e",
    "/styles/theme.css.map": "/styles/theme.css.map?id=9c7df61cd89a92c5e0a8",
    "/styles/editor.css.map": "/styles/editor.css.map?id=69d6a70bbda83264bb86",
    "/scripts/theme.js": "/scripts/theme.js?id=3434d1d634c538a3a119",
    "/scripts/theme.js.map": "/scripts/theme.js.map?id=09a45080fc639f865d2c",
    "/scripts/theme.js.LICENSE.txt": "/scripts/theme.js.LICENSE.txt?id=ee51d5c87929cafa4ad0",
    "/images/404.svg": "/images/404.svg?id=fd408b76768473043d47",
    "/images/logo.svg": "/images/logo.svg?id=f55f7c6033a579dbede7",
    "/images/right-arrow.svg": "/images/right-arrow.svg?id=0e888678d2ceba105e65",
    "/images/footer-logo.svg": "/images/footer-logo.svg?id=52851cea0402dbd1657a",
    "/images/linkedin.svg": "/images/linkedin.svg?id=3904a4506e8dcb2afbd0",
    "/images/whoops.svg": "/images/whoops.svg?id=6dc46257bb32f5c2b43e",
    "/images/twitter.svg": "/images/twitter.svg?id=6c331622ead629b82195"
}
